[
    {
        "id": "471327",
        "document_type": false,
        "expired_campaign": false,
        "publication": null,
        "subject": null,
        "name_with_parent": null,
        "collections": false,
        "url": "<a href='/participa' target='_blank' data-origin='result-fake-290'> Participa  </a>",
        "searchable_type": "FakeSearchDocument",
        "official_document_type": null,
        "page_kind": "service",
        "content_sub_title_card": "Presidencia del Consejo de Ministros",
        "content": "Participa es un espacio para fomentar la colaboraci\u00f3n de todos los peruanos en el logro de los objetivos del pa\u00eds. Esta iniciativa del Laboratorio de Gobierno y Trans ...",
        "image_url": null,
        "action_url": null,
        "children_pages": null,
        "fake_type": "Page",
        "disabled": null,
        "score": 1560.0,
        "last_week_visits": 0
    },
    {
        "id": "1088208",
        "document_type": false,
        "expired_campaign": false,
        "publication": null,
        "subject": null,
        "name_with_parent": "Direcci\u00f3n de Salud Virgen de Cocharcas - Chincheros  - regionapurimac-risvirgendecocharcas",
        "collections": false,
        "url": "<a class=\"track-ga-click\" data-origin=\"result-institution-3306\" href=\"/regionapurimac-risvirgendecocharcas\">Direcci\u00f3n de Salud Virgen de Cocharcas - Chincheros  - regionapurimac-risvirgendecocharcas</a>",
        "searchable_type": "Institution",
        "official_document_type": null,
        "page_kind": null,
        "content_sub_title_card": null,
        "content": "",
        "image_url": null,
        "action_url": null,
        "children_pages": null,
        "fake_type": null,
        "disabled": null,
        "score": 132.0,
        "last_week_visits": 0
    },
    {
        "id": "1086410",
        "document_type": false,
        "expired_campaign": false,
        "publication": null,
        "subject": null,
        "name_with_parent": "Corte Superior de Justicia de Puente Piedra - Ventanilla - CSJPPV",
        "collections": false,
        "url": "<a class=\"track-ga-click\" data-origin=\"result-institution-3387\" href=\"/csjpuentepiedra-ventanilla\">Corte Superior de Justicia de Puente Piedra - Ventanilla - CSJPPV</a>",
        "searchable_type": "Institution",
        "official_document_type": null,
        "page_kind": null,
        "content_sub_title_card": null,
        "content": "",
        "image_url": null,
        "action_url": null,
        "children_pages": null,
        "fake_type": null,
        "disabled": null,
        "score": 132.0,
        "last_week_visits": 0
    },
    {
        "id": "1453995",
        "document_type": false,
        "expired_campaign": false,
        "publication": null,
        "subject": null,
        "name_with_parent": "Unidad Ejecutora 404 Red de Salud Acobamba - UERSA",
        "collections": false,
        "url": "<a class=\"track-ga-click\" data-origin=\"result-institution-3547\" href=\"/risacobamba\">Unidad Ejecutora 404 Red de Salud Acobamba - UERSA</a>",
        "searchable_type": "Institution",
        "official_document_type": null,
        "page_kind": null,
        "content_sub_title_card": null,
        "content": "",
        "image_url": null,
        "action_url": null,
        "children_pages": null,
        "fake_type": null,
        "disabled": null,
        "score": 132.0,
        "last_week_visits": 0
    },
    {
        "id": "452023",
        "document_type": false,
        "expired_campaign": false,
        "publication": null,
        "subject": null,
        "name_with_parent": "Gerencia Regional de Educaci\u00f3n La Libertad - GRELL",
        "collections": false,
        "url": "<a class=\"track-ga-click\" data-origin=\"result-institution-3285\" href=\"/grell\">Gerencia Regional de Educaci\u00f3n La Libertad - GRELL</a>",
        "searchable_type": "Institution",
        "official_document_type": null,
        "page_kind": null,
        "content_sub_title_card": null,
        "content": "",
        "image_url": null,
        "action_url": null,
        "children_pages": null,
        "fake_type": null,
        "disabled": null,
        "score": 132.0,
        "last_week_visits": 0
    },
    {
        "id": "379681",
        "document_type": false,
        "expired_campaign": false,
        "publication": null,
        "subject": null,
        "name_with_parent": "Municipalidad Distrital de Carhuamayo - MDC",
        "collections": false,
        "url": "<a class=\"track-ga-click\" data-origin=\"result-institution-2099\" href=\"/municarhuamayo\">Municipalidad Distrital de Carhuamayo - MDC</a>",
        "searchable_type": "Institution",
        "official_document_type": null,
        "page_kind": null,
        "content_sub_title_card": null,
        "content": "",
        "image_url": null,
        "action_url": null,
        "children_pages": null,
        "fake_type": null,
        "disabled": null,
        "score": 132.0,
        "last_week_visits": 0
    },
    {
        "id": "379695",
        "document_type": false,
        "expired_campaign": false,
        "publication": null,
        "subject": null,
        "name_with_parent": "Municipalidad Distrital de Pampa Hermosa Satipo (Mdph) - MDPH",
        "collections": false,
        "url": "<a class=\"track-ga-click\" data-origin=\"result-institution-2106\" href=\"/municipalidad-distrital-de-pampa-hermosa-satipo-mdph\">Municipalidad Distrital de Pampa Hermosa Satipo (Mdph) - MDPH</a>",
        "searchable_type": "Institution",
        "official_document_type": null,
        "page_kind": null,
        "content_sub_title_card": null,
        "content": "",
        "image_url": null,
        "action_url": null,
        "children_pages": null,
        "fake_type": null,
        "disabled": null,
        "score": 132.0,
        "last_week_visits": 0
    },
    {
        "id": "379711",
        "document_type": false,
        "expired_campaign": false,
        "publication": null,
        "subject": null,
        "name_with_parent": "Municipalidad Distrital de La Uni\u00f3n - Tarma - MDLU",
        "collections": false,
        "url": "<a class=\"track-ga-click\" data-origin=\"result-institution-2114\" href=\"/munilaunion-tarma\">Municipalidad Distrital de La Uni\u00f3n - Tarma - MDLU</a>",
        "searchable_type": "Institution",
        "official_document_type": null,
        "page_kind": null,
        "content_sub_title_card": null,
        "content": "",
        "image_url": null,
        "action_url": null,
        "children_pages": null,
        "fake_type": null,
        "disabled": null,
        "score": 132.0,
        "last_week_visits": 0
    },
    {
        "id": "379721",
        "document_type": false,
        "expired_campaign": false,
        "publication": null,
        "subject": null,
        "name_with_parent": "Municipalidad Distrital de Chacapalpa",
        "collections": false,
        "url": "<a class=\"track-ga-click\" data-origin=\"result-institution-2119\" href=\"/municipalidad-distrital-de-chacapalpa\">Municipalidad Distrital de Chacapalpa</a>",
        "searchable_type": "Institution",
        "official_document_type": null,
        "page_kind": null,
        "content_sub_title_card": null,
        "content": "",
        "image_url": null,
        "action_url": null,
        "children_pages": null,
        "fake_type": null,
        "disabled": null,
        "score": 132.0,
        "last_week_visits": 0
    },
    {
        "id": "379723",
        "document_type": false,
        "expired_campaign": false,
        "publication": null,
        "subject": null,
        "name_with_parent": "Municipalidad Distrital de Huay Huay",
        "collections": false,
        "url": "<a class=\"track-ga-click\" data-origin=\"result-institution-2120\" href=\"/municipalidad-distrital-de-huay-huay\">Municipalidad Distrital de Huay Huay</a>",
        "searchable_type": "Institution",
        "official_document_type": null,
        "page_kind": null,
        "content_sub_title_card": null,
        "content": "",
        "image_url": null,
        "action_url": null,
        "children_pages": null,
        "fake_type": null,
        "disabled": null,
        "score": 132.0,
        "last_week_visits": 0
    },
    {
        "id": "379725",
        "document_type": false,
        "expired_campaign": false,
        "publication": null,
        "subject": null,
        "name_with_parent": "Municipalidad Distrital de Marcapomacocha",
        "collections": false,
        "url": "<a class=\"track-ga-click\" data-origin=\"result-institution-2121\" href=\"/municipalidad-distrital-de-marcapomacocha\">Municipalidad Distrital de Marcapomacocha</a>",
        "searchable_type": "Institution",
        "official_document_type": null,
        "page_kind": null,
        "content_sub_title_card": null,
        "content": "",
        "image_url": null,
        "action_url": null,
        "children_pages": null,
        "fake_type": null,
        "disabled": null,
        "score": 132.0,
        "last_week_visits": 0
    },
    {
        "id": "379729",
        "document_type": false,
        "expired_campaign": false,
        "publication": null,
        "subject": null,
        "name_with_parent": "Municipalidad Distrital de Paccha (Mdp) - MDP",
        "collections": false,
        "url": "<a class=\"track-ga-click\" data-origin=\"result-institution-2123\" href=\"/municipalidad-distrital-de-paccha-mdp\">Municipalidad Distrital de Paccha (Mdp) - MDP</a>",
        "searchable_type": "Institution",
        "official_document_type": null,
        "page_kind": null,
        "content_sub_title_card": null,
        "content": "",
        "image_url": null,
        "action_url": null,
        "children_pages": null,
        "fake_type": null,
        "disabled": null,
        "score": 132.0,
        "last_week_visits": 0
    },
    {
        "id": "379731",
        "document_type": false,
        "expired_campaign": false,
        "publication": null,
        "subject": null,
        "name_with_parent": "Municipalidad Distrital de Santa B\u00e1rbara de Carhuacay\u00e1n - MDSBC",
        "collections": false,
        "url": "<a class=\"track-ga-click\" data-origin=\"result-institution-2124\" href=\"/munisantabarbara\">Municipalidad Distrital de Santa B\u00e1rbara de Carhuacay\u00e1n - MDSBC</a>",
        "searchable_type": "Institution",
        "official_document_type": null,
        "page_kind": null,
        "content_sub_title_card": null,
        "content": "",
        "image_url": null,
        "action_url": null,
        "children_pages": null,
        "fake_type": null,
        "disabled": null,
        "score": 132.0,
        "last_week_visits": 0
    },
    {
        "id": "379733",
        "document_type": false,
        "expired_campaign": false,
        "publication": null,
        "subject": null,
        "name_with_parent": "Municipalidad Distrital Santa Rosa de Sacco - MDSRS",
        "collections": false,
        "url": "<a class=\"track-ga-click\" data-origin=\"result-institution-2125\" href=\"/munisantarosadesacco\">Municipalidad Distrital Santa Rosa de Sacco - MDSRS</a>",
        "searchable_type": "Institution",
        "official_document_type": null,
        "page_kind": null,
        "content_sub_title_card": null,
        "content": "",
        "image_url": null,
        "action_url": null,
        "children_pages": null,
        "fake_type": null,
        "disabled": null,
        "score": 132.0,
        "last_week_visits": 0
    },
    {
        "id": "379735",
        "document_type": false,
        "expired_campaign": false,
        "publication": null,
        "subject": null,
        "name_with_parent": "Municipalidad Distrital de Suitucancha (Mdsuitucancha) - MDSuitucancha",
        "collections": false,
        "url": "<a class=\"track-ga-click\" data-origin=\"result-institution-2126\" href=\"/municipalidad-distrital-de-suitucancha-mdsuitucancha\">Municipalidad Distrital de Suitucancha (Mdsuitucancha) - MDSuitucancha</a>",
        "searchable_type": "Institution",
        "official_document_type": null,
        "page_kind": null,
        "content_sub_title_card": null,
        "content": "",
        "image_url": null,
        "action_url": null,
        "children_pages": null,
        "fake_type": null,
        "disabled": null,
        "score": 132.0,
        "last_week_visits": 0
    },
    {
        "id": "379737",
        "document_type": false,
        "expired_campaign": false,
        "publication": null,
        "subject": null,
        "name_with_parent": "Municipalidad Distrital de Yauli - Jun\u00edn - MDY",
        "collections": false,
        "url": "<a class=\"track-ga-click\" data-origin=\"result-institution-2127\" href=\"/muniyauli-junin\">Municipalidad Distrital de Yauli - Jun\u00edn - MDY</a>",
        "searchable_type": "Institution",
        "official_document_type": null,
        "page_kind": null,
        "content_sub_title_card": null,
        "content": "",
        "image_url": null,
        "action_url": null,
        "children_pages": null,
        "fake_type": null,
        "disabled": null,
        "score": 132.0,
        "last_week_visits": 0
    },
    {
        "id": "379745",
        "document_type": false,
        "expired_campaign": false,
        "publication": null,
        "subject": null,
        "name_with_parent": "Municipalidad Distrital de Chocope (Mdch) - MDCH",
        "collections": false,
        "url": "<a class=\"track-ga-click\" data-origin=\"result-institution-2131\" href=\"/municipalidad-distrital-de-chocope-mdch\">Municipalidad Distrital de Chocope (Mdch) - MDCH</a>",
        "searchable_type": "Institution",
        "official_document_type": null,
        "page_kind": null,
        "content_sub_title_card": null,
        "content": "",
        "image_url": null,
        "action_url": null,
        "children_pages": null,
        "fake_type": null,
        "disabled": null,
        "score": 132.0,
        "last_week_visits": 0
    },
    {
        "id": "379757",
        "document_type": false,
        "expired_campaign": false,
        "publication": null,
        "subject": null,
        "name_with_parent": "Municipalidad Distrital de Bambamarca - MDB",
        "collections": false,
        "url": "<a class=\"track-ga-click\" data-origin=\"result-institution-2137\" href=\"/munibambamarca\">Municipalidad Distrital de Bambamarca - MDB</a>",
        "searchable_type": "Institution",
        "official_document_type": null,
        "page_kind": null,
        "content_sub_title_card": null,
        "content": "",
        "image_url": null,
        "action_url": null,
        "children_pages": null,
        "fake_type": null,
        "disabled": null,
        "score": 132.0,
        "last_week_visits": 0
    },
    {
        "id": "379759",
        "document_type": false,
        "expired_campaign": false,
        "publication": null,
        "subject": null,
        "name_with_parent": "Municipalidad Distrital de Condormarca - MDC",
        "collections": false,
        "url": "<a class=\"track-ga-click\" data-origin=\"result-institution-2138\" href=\"/municondormarca\">Municipalidad Distrital de Condormarca - MDC</a>",
        "searchable_type": "Institution",
        "official_document_type": null,
        "page_kind": null,
        "content_sub_title_card": null,
        "content": "",
        "image_url": null,
        "action_url": null,
        "children_pages": null,
        "fake_type": null,
        "disabled": null,
        "score": 132.0,
        "last_week_visits": 0
    },
    {
        "id": "379761",
        "document_type": false,
        "expired_campaign": false,
        "publication": null,
        "subject": null,
        "name_with_parent": "Municipalidad Distrital de Longotea",
        "collections": false,
        "url": "<a class=\"track-ga-click\" data-origin=\"result-institution-2139\" href=\"/municipalidad-distrital-de-longotea\">Municipalidad Distrital de Longotea</a>",
        "searchable_type": "Institution",
        "official_document_type": null,
        "page_kind": null,
        "content_sub_title_card": null,
        "content": "",
        "image_url": null,
        "action_url": null,
        "children_pages": null,
        "fake_type": null,
        "disabled": null,
        "score": 132.0,
        "last_week_visits": 0
    },
    {
        "id": "379763",
        "document_type": false,
        "expired_campaign": false,
        "publication": null,
        "subject": null,
        "name_with_parent": "Municipalidad Distrital de Uchumarca - MDU",
        "collections": false,
        "url": "<a class=\"track-ga-click\" data-origin=\"result-institution-2140\" href=\"/muniuchumarca\">Municipalidad Distrital de Uchumarca - MDU</a>",
        "searchable_type": "Institution",
        "official_document_type": null,
        "page_kind": null,
        "content_sub_title_card": null,
        "content": "",
        "image_url": null,
        "action_url": null,
        "children_pages": null,
        "fake_type": null,
        "disabled": null,
        "score": 132.0,
        "last_week_visits": 0
    },
    {
        "id": "379765",
        "document_type": false,
        "expired_campaign": false,
        "publication": null,
        "subject": null,
        "name_with_parent": "Municipalidad Distrital de Ucuncha (Md Ucuncha) - MD-UCUNCHA",
        "collections": false,
        "url": "<a class=\"track-ga-click\" data-origin=\"result-institution-2141\" href=\"/municipalidad-distrital-de-ucuncha-md-ucuncha\">Municipalidad Distrital de Ucuncha (Md Ucuncha) - MD-UCUNCHA</a>",
        "searchable_type": "Institution",
        "official_document_type": null,
        "page_kind": null,
        "content_sub_title_card": null,
        "content": "",
        "image_url": null,
        "action_url": null,
        "children_pages": null,
        "fake_type": null,
        "disabled": null,
        "score": 132.0,
        "last_week_visits": 0
    },
    {
        "id": "379775",
        "document_type": false,
        "expired_campaign": false,
        "publication": null,
        "subject": null,
        "name_with_parent": "Municipalidad Distrital de Lucma - Gran Chim\u00fa - MDL",
        "collections": false,
        "url": "<a class=\"track-ga-click\" data-origin=\"result-institution-2146\" href=\"/munilucma-granchimu\">Municipalidad Distrital de Lucma - Gran Chim\u00fa - MDL</a>",
        "searchable_type": "Institution",
        "official_document_type": null,
        "page_kind": null,
        "content_sub_title_card": null,
        "content": "",
        "image_url": null,
        "action_url": null,
        "children_pages": null,
        "fake_type": null,
        "disabled": null,
        "score": 132.0,
        "last_week_visits": 0
    },
    {
        "id": "379779",
        "document_type": false,
        "expired_campaign": false,
        "publication": null,
        "subject": null,
        "name_with_parent": "Municipalidad Distrital de Sayapullo",
        "collections": false,
        "url": "<a class=\"track-ga-click\" data-origin=\"result-institution-2148\" href=\"/municipalidad-distrital-de-sayapullo\">Municipalidad Distrital de Sayapullo</a>",
        "searchable_type": "Institution",
        "official_document_type": null,
        "page_kind": null,
        "content_sub_title_card": null,
        "content": "",
        "image_url": null,
        "action_url": null,
        "children_pages": null,
        "fake_type": null,
        "disabled": null,
        "score": 132.0,
        "last_week_visits": 0
    },
    {
        "id": "379787",
        "document_type": false,
        "expired_campaign": false,
        "publication": null,
        "subject": null,
        "name_with_parent": "Municipalidad Distrital de Huaso - MDH",
        "collections": false,
        "url": "<a class=\"track-ga-click\" data-origin=\"result-institution-2152\" href=\"/munihuaso\">Municipalidad Distrital de Huaso - MDH</a>",
        "searchable_type": "Institution",
        "official_document_type": null,
        "page_kind": null,
        "content_sub_title_card": null,
        "content": "",
        "image_url": null,
        "action_url": null,
        "children_pages": null,
        "fake_type": null,
        "disabled": null,
        "score": 132.0,
        "last_week_visits": 0
    }
]